gen/__init__.py
gen/programs.py
genai_bit-0.1.1.dist-info/METADATA
genai_bit-0.1.1.dist-info/WHEEL
genai_bit-0.1.1.dist-info/top_level.txt
genai_bit-0.1.1.dist-info/RECORD
